MANIFEST.in
README.md
requirements.txt
setup.cfg
setup.py
grpcool/__init__.py
grpcool.egg-info/PKG-INFO
grpcool.egg-info/SOURCES.txt
grpcool.egg-info/dependency_links.txt
grpcool.egg-info/requires.txt
grpcool.egg-info/top_level.txt
grpcool/connection/__init__.py